LICENSE
README.md
setup.py
rock_search/__init__.py
rock_search/index.py
rock_search/version.py
rock_search.egg-info/PKG-INFO
rock_search.egg-info/SOURCES.txt
rock_search.egg-info/dependency_links.txt
rock_search.egg-info/requires.txt
rock_search.egg-info/top_level.txt