Metadata-Version: 2.1
Name: rock-search
Version: 0.0.1
Summary: Rockflow data search
Home-page: https://github.com/day253/rock-search
Author: Junkai Dai
Author-email: daijunkai@flowcapai.com
License: UNKNOWN
Keywords: elasticsearch
Platform: any
License-File: LICENSE
